milestones/__init__.py
milestones/admin.py
milestones/api.py
milestones/data.py
milestones/exceptions.py
milestones/models.py
milestones/resources.py
milestones/serializers.py
milestones/services.py
milestones/urls.py
milestones/validators.py
milestones/views.py
milestones/management/__init__.py
milestones/management/commands/__init__.py
milestones/management/commands/tests/__init__.py
milestones/migrations/0001_initial.py
milestones/migrations/0002_data__seed_relationship_types.py
milestones/migrations/0003_coursecontentmilestone_requirements.py
milestones/migrations/0004_auto_20151221_1445.py
milestones/migrations/__init__.py
milestones/tests/__init__.py
milestones/tests/test_api.py
milestones/tests/test_data.py
milestones/tests/test_model.py
milestones/tests/test_services.py
milestones/tests/utils.py
milestones/tests/mocks/__init__.py
milestones/tests/mocks/resources.py
edx_milestones-1.1.0.dist-info/AUTHORS
edx_milestones-1.1.0.dist-info/LICENSE
edx_milestones-1.1.0.dist-info/METADATA
edx_milestones-1.1.0.dist-info/WHEEL
edx_milestones-1.1.0.dist-info/top_level.txt
edx_milestones-1.1.0.dist-info/RECORD
