Metadata-Version: 2.2
Name: edx-milestones
Version: 1.1.0
Summary: Significant events module for Open edX
Home-page: https://github.com/openedx/edx-milestones
Author: edX
License: AGPL
Classifier: Development Status :: 5 - Production/Stable
Classifier: Environment :: Web Environment
Classifier: Intended Audience :: Developers
Classifier: License :: OSI Approved :: GNU Affero General Public License v3
Classifier: Operating System :: OS Independent
Classifier: Programming Language :: Python
Classifier: Programming Language :: Python :: 3
Classifier: Programming Language :: Python :: 3.11
Classifier: Programming Language :: Python :: 3.12
Classifier: Framework :: Django
Classifier: Framework :: Django :: 4.2
Classifier: Framework :: Django :: 5.2
License-File: LICENSE
License-File: AUTHORS
Requires-Dist: Django
Requires-Dist: django-model-utils
Requires-Dist: edx-opaque-keys>=0.2.1
Requires-Dist: setuptools
Requires-Dist: six
Dynamic: author
Dynamic: classifier
Dynamic: description
Dynamic: description-content-type
Dynamic: home-page
Dynamic: license
Dynamic: requires-dist
Dynamic: summary
